preflight-0.2.0.dist-info/top_level.txt
preflight-0.2.0.dist-info/metadata.json
preflight-0.2.0.dist-info/RECORD
preflight-0.2.0.dist-info/entry_points.txt
preflight-0.2.0.dist-info/DESCRIPTION.rst
preflight-0.2.0.dist-info/WHEEL
preflight-0.2.0.dist-info/METADATA
preflight/checks.py
preflight/exceptions.py
preflight/version.py
preflight/__main__.py
preflight/config.py
preflight/__init__.py
preflight/utils.py
