Metadata-Version: 2.0
Name: preflight
Version: 0.2.0
Summary: Checks that a site has been deployed correctly
Home-page: https://bitbucket.org/takeflight/preflight/
Author: Tim Heap
Author-email: hello@takeflight.com.au
License: BSD License
Platform: UNKNOWN
Classifier: Environment :: Web Environment
Classifier: Intended Audience :: Developers
Classifier: Operating System :: OS Independent
Classifier: Programming Language :: Python
Classifier: Framework :: Django
Classifier: License :: OSI Approved :: BSD License
Requires-Dist: requests (==2.8.0)
Requires-Dist: accept-types (==0.3.0)
Requires-Dist: requests (==2.8.0)
Requires-Dist: beautifulsoup4 (==4.4.0)
